{"nodes": [{"id": "routes_url_getshorten", "label": "GET /shorten Handler", "file_type": "code", "source_file": "routes/url.js", "source_location": "14-16", "source_url": null, "captured_at": null, "author": null, "contributor": null}, {"id": "routes_url_postshorten", "label": "POST /shorten URL Creation Handler", "file_type": "code", "source_file": "routes/url.js", "source_location": "20-63", "source_url": null, "captured_at": null, "author": null, "contributor": null}, {"id": "url_deduplication_pattern", "label": "URL Deduplication Pattern", "file_type": "rationale", "source_file": "routes/url.js", "source_location": "38-42", "source_url": null, "captured_at": null, "author": null, "contributor": null}, {"id": "shortid_generation", "label": "Short ID Generation via shortid", "file_type": "concept", "source_file": "routes/url.js", "source_location": "33", "source_url": null, "captured_at": null, "author": null, "contributor": null}], "edges": [{"source": "routes_url_postshorten", "target": "models_url_urlmodel", "relation": "calls", "confidence": "EXTRACTED", "confidence_score": 1.0, "source_file": "routes/url.js", "source_location": "38,44-51", "weight": 1.0}, {"source": "routes_url_postshorten", "target": "shortid_generation", "relation": "references", "confidence": "EXTRACTED", "confidence_score": 1.0, "source_file": "routes/url.js", "source_location": "33", "weight": 1.0}, {"source": "routes_url_postshorten", "target": "url_deduplication_pattern", "relation": "implements", "confidence": "EXTRACTED", "confidence_score": 1.0, "source_file": "routes/url.js", "source_location": "38-54", "weight": 1.0}, {"source": "routes_url_getshorten", "target": "public_home_form", "relation": "references", "confidence": "EXTRACTED", "confidence_score": 1.0, "source_file": "routes/url.js", "source_location": "15", "weight": 1.0}, {"source": "routes_url_postshorten", "target": "url_shortener_service", "relation": "implements", "confidence": "INFERRED", "confidence_score": 0.85, "source_file": "routes/url.js", "source_location": null, "weight": 1.0}], "hyperedges": [{"id": "url_shorten_flow", "label": "URL Shortening Request Flow", "nodes": ["public_home_form", "routes_url_postshorten", "models_url_urlmodel"], "relation": "participate_in", "confidence": "EXTRACTED", "confidence_score": 1.0, "source_file": "routes/url.js"}]}